MANIFEST.in
README.rst
setup.cfg
setup.py
persistent_pineapple/__init__.py
persistent_pineapple/_json.py
persistent_pineapple.egg-info/PKG-INFO
persistent_pineapple.egg-info/SOURCES.txt
persistent_pineapple.egg-info/dependency_links.txt
persistent_pineapple.egg-info/top_level.txt
persistent_pineapple.egg-info/zip-safe
persistent_pineapple/tests/__init__.py
persistent_pineapple/tests/json_checks.py
persistent_pineapple/tests/sanity_checks.py
persistent_pineapple/tests/test_comment.py