Metadata-Version: 1.1
Name: persistent-pineapple
Version: 1.0.0
Summary: JSON Settings
Home-page: https://github.com/JasonAUnrein/Persistent-Pineapple
Author: Timothy McFadden
Author-email: UNKNOWN
License: UNKNOWN
Download-URL: https://github.com/JasonAUnrein/Persistent-Pineapple/releases/Persistent-Pineapple-1.0.0.tar.gz
Platform: UNKNOWN
Classifier: Development Status :: 5 - Production/Stable
Classifier: Environment :: Other Environment
Classifier: License :: OSI Approved :: MIT License
Classifier: Programming Language :: Python
Classifier: Programming Language :: Python :: 2
Classifier: Programming Language :: Python :: 2.6
Classifier: Programming Language :: Python :: 2.7
Classifier: Programming Language :: Python :: 3
Classifier: Programming Language :: Python :: 3.2
Classifier: Programming Language :: Python :: 3.3
Classifier: Programming Language :: Python :: 3.4
Classifier: Intended Audience :: Developers
Classifier: Environment :: Console
Classifier: Natural Language :: English
Classifier: Operating System :: OS Independent
Classifier: Topic :: Software Development :: Libraries
